whacamolefinder/README.MD
whacamolefinder/__init__.py
whacamolefinder/requirements.txt
whacamolefinder/thirdparty.json
whacamolefinder-0.11.dist-info/LICENSE.rst
whacamolefinder-0.11.dist-info/METADATA
whacamolefinder-0.11.dist-info/WHEEL
whacamolefinder-0.11.dist-info/top_level.txt
whacamolefinder-0.11.dist-info/RECORD
