Metadata-Version: 2.1
Name: whacamolefinder
Version: 0.11
Summary: Get the difference between 2 images
Home-page: https://github.com/hansalemaos/whacamolefinder
Author: Johannes Fischer
Author-email: aulasparticularesdealemaosp@gmail.com
License: MIT
Keywords: whac-a-mole,compare,images
Classifier: Development Status :: 4 - Beta
Classifier: Programming Language :: Python :: 3 :: Only
Classifier: Programming Language :: Python :: 3.10
Classifier: Topic :: Software Development :: Libraries :: Python Modules
Classifier: Topic :: Utilities
License-File: LICENSE.rst
Requires-Dist: a-cv2-easy-resize
Requires-Dist: a-cv-imwrite-imread-plus
Requires-Dist: numexpr
Requires-Dist: numpy
Requires-Dist: opencv-python
